README.rst
setup.py
aliyun_fc2.egg-info/PKG-INFO
aliyun_fc2.egg-info/SOURCES.txt
aliyun_fc2.egg-info/dependency_links.txt
aliyun_fc2.egg-info/requires.txt
aliyun_fc2.egg-info/top_level.txt
fc2/__init__.py
fc2/auth.py
fc2/client.py
fc2/fc_exceptions.py
fc2/util.py